catcall/__init__.py
catcall/cli.py
catcall-1.0.0.dist-info/licenses/LICENSE
catcall-1.0.0.dist-info/METADATA
catcall-1.0.0.dist-info/WHEEL
catcall-1.0.0.dist-info/entry_points.txt
catcall-1.0.0.dist-info/top_level.txt
catcall-1.0.0.dist-info/RECORD
