Metadata-Version: 2.4
Name: catcall
Version: 1.0.0
Summary: Display random cats from CATAAS as high-resolution ASCII art in the #justparchment8 palette
Author-email: Amber Williams <amber@example.com>
License: MIT
Project-URL: Homepage, https://github.com/amberstarlight/catcall
Project-URL: Repository, https://github.com/amberstarlight/catcall
Project-URL: Issues, https://github.com/amberstarlight/catcall/issues
Keywords: cat,ascii,art,terminal,cli,cataas,justparchment8
Classifier: Development Status :: 5 - Production/Stable
Classifier: Environment :: Console
Classifier: Intended Audience :: Developers
Classifier: Intended Audience :: End Users/Desktop
Classifier: Operating System :: OS Independent
Classifier: Programming Language :: Python :: 3
Classifier: Programming Language :: Python :: 3.8
Classifier: Programming Language :: Python :: 3.9
Classifier: Programming Language :: Python :: 3.10
Classifier: Programming Language :: Python :: 3.11
Classifier: Programming Language :: Python :: 3.12
Classifier: Topic :: Artistic Software
Classifier: Topic :: Multimedia :: Graphics
Classifier: Topic :: Terminals
Requires-Python: >=3.8
License-File: LICENSE
Requires-Dist: requests>=2.25.0
Requires-Dist: Pillow>=8.0.0
Dynamic: license-file
